native/ntcore/_init_robotpy_native_ntcore.py
native/ntcore/robotpy-native-ntcore.pc
native/ntcore/include/ntcore.h
native/ntcore/include/ntcore_c.h
native/ntcore/include/ntcore_c_types.h
native/ntcore/include/ntcore_cpp.h
native/ntcore/include/ntcore_cpp_types.h
native/ntcore/include/ntcore_test.h
native/ntcore/include/networktables/BooleanArrayTopic.h
native/ntcore/include/networktables/BooleanTopic.h
native/ntcore/include/networktables/DoubleArrayTopic.h
native/ntcore/include/networktables/DoubleTopic.h
native/ntcore/include/networktables/FloatArrayTopic.h
native/ntcore/include/networktables/FloatTopic.h
native/ntcore/include/networktables/GenericEntry.h
native/ntcore/include/networktables/IntegerArrayTopic.h
native/ntcore/include/networktables/IntegerTopic.h
native/ntcore/include/networktables/MultiSubscriber.h
native/ntcore/include/networktables/NTSendable.h
native/ntcore/include/networktables/NTSendableBuilder.h
native/ntcore/include/networktables/NetworkTable.h
native/ntcore/include/networktables/NetworkTableEntry.h
native/ntcore/include/networktables/NetworkTableInstance.h
native/ntcore/include/networktables/NetworkTableListener.h
native/ntcore/include/networktables/NetworkTableType.h
native/ntcore/include/networktables/NetworkTableValue.h
native/ntcore/include/networktables/ProtobufTopic.h
native/ntcore/include/networktables/RawTopic.h
native/ntcore/include/networktables/StringArrayTopic.h
native/ntcore/include/networktables/StringTopic.h
native/ntcore/include/networktables/StructArrayTopic.h
native/ntcore/include/networktables/StructTopic.h
native/ntcore/include/networktables/Topic.h
native/ntcore/include/networktables/UnitTopic.h
native/ntcore/lib/libntcore.dylib
robotpy_native_ntcore-2025.3.2.dist-info/METADATA
robotpy_native_ntcore-2025.3.2.dist-info/WHEEL
robotpy_native_ntcore-2025.3.2.dist-info/entry_points.txt
robotpy_native_ntcore-2025.3.2.dist-info/RECORD
