Metadata-Version: 2.4
Name: robotpy-native-ntcore
Version: 2025.3.2
Summary: WPILib NetworkTables Library
License-Expression: BSD-3-Clause
Requires-Dist: robotpy-native-wpinet==2025.3.2
Requires-Dist: robotpy-native-wpiutil==2025.3.2
